<?xml version="1.0" encoding="UTF-8"?>
<!DOCTYPE mapper PUBLIC "-//mybatis.org//DTD Mapper 3.0//EN" "http://mybatis.org/dtd/mybatis-3-mapper.dtd">
<mapper namespace="com.russellzhou.trade.data.dao.UserInfoMapper">
  <resultMap id="BaseResultMap" type="com.russellzhou.trade.data.entity.UserInfo">
    <!--
      WARNING - @mbg.generated
      This element is automatically generated by MyBatis Generator, do not modify.
    -->
    <id column="id" jdbcType="BIGINT" property="id" />
    <result column="user_account" jdbcType="VARCHAR" property="userAccount" />
    <result column="user_password" jdbcType="VARCHAR" property="userPassword" />
    <result column="user_name" jdbcType="VARCHAR" property="userName" />
    <result column="email" jdbcType="VARCHAR" property="email" />
    <result column="mobile" jdbcType="VARCHAR" property="mobile" />
    <result column="is_del" jdbcType="TINYINT" property="isDel" />
    <result column="create_time" jdbcType="TIMESTAMP" property="createTime" />
    <result column="modify_time" jdbcType="TIMESTAMP" property="modifyTime" />
  </resultMap>
  <sql id="Base_Column_List">
    <!--
      WARNING - @mbg.generated
      This element is automatically generated by MyBatis Generator, do not modify.
    -->
    id, user_account, user_password, user_name, email, mobile, is_del, create_time, modify_time
  </sql>
  <select id="selectByPrimaryKey" parameterType="java.lang.Long" resultMap="BaseResultMap">
    <!--
      WARNING - @mbg.generated
      This element is automatically generated by MyBatis Generator, do not modify.
    -->
    select 
    <include refid="Base_Column_List" />
    from user_info
    where id = #{id,jdbcType=BIGINT}
  </select>
  <delete id="deleteByPrimaryKey" parameterType="java.lang.Long">
    <!--
      WARNING - @mbg.generated
      This element is automatically generated by MyBatis Generator, do not modify.
    -->
    delete from user_info
    where id = #{id,jdbcType=BIGINT}
  </delete>
  <insert id="insert" parameterType="com.russellzhou.trade.data.entity.UserInfo">
    <!--
      WARNING - @mbg.generated
      This element is automatically generated by MyBatis Generator, do not modify.
    -->
    insert into user_info (id, user_account, user_password, 
      user_name, email, mobile, 
      is_del, create_time, modify_time
      )
    values (#{id,jdbcType=BIGINT}, #{userAccount,jdbcType=VARCHAR}, #{userPassword,jdbcType=VARCHAR}, 
      #{userName,jdbcType=VARCHAR}, #{email,jdbcType=VARCHAR}, #{mobile,jdbcType=VARCHAR}, 
      #{isDel,jdbcType=TINYINT}, #{createTime,jdbcType=TIMESTAMP}, #{modifyTime,jdbcType=TIMESTAMP}
      )
  </insert>
  <insert id="insertSelective" parameterType="com.russellzhou.trade.data.entity.UserInfo">
    <!--
      WARNING - @mbg.generated
      This element is automatically generated by MyBatis Generator, do not modify.
    -->
    insert into user_info
    <trim prefix="(" suffix=")" suffixOverrides=",">
      <if test="id != null">
        id,
      </if>
      <if test="userAccount != null">
        user_account,
      </if>
      <if test="userPassword != null">
        user_password,
      </if>
      <if test="userName != null">
        user_name,
      </if>
      <if test="email != null">
        email,
      </if>
      <if test="mobile != null">
        mobile,
      </if>
      <if test="isDel != null">
        is_del,
      </if>
      <if test="createTime != null">
        create_time,
      </if>
      <if test="modifyTime != null">
        modify_time,
      </if>
    </trim>
    <trim prefix="values (" suffix=")" suffixOverrides=",">
      <if test="id != null">
        #{id,jdbcType=BIGINT},
      </if>
      <if test="userAccount != null">
        #{userAccount,jdbcType=VARCHAR},
      </if>
      <if test="userPassword != null">
        #{userPassword,jdbcType=VARCHAR},
      </if>
      <if test="userName != null">
        #{userName,jdbcType=VARCHAR},
      </if>
      <if test="email != null">
        #{email,jdbcType=VARCHAR},
      </if>
      <if test="mobile != null">
        #{mobile,jdbcType=VARCHAR},
      </if>
      <if test="isDel != null">
        #{isDel,jdbcType=TINYINT},
      </if>
      <if test="createTime != null">
        #{createTime,jdbcType=TIMESTAMP},
      </if>
      <if test="modifyTime != null">
        #{modifyTime,jdbcType=TIMESTAMP},
      </if>
    </trim>
  </insert>
  <update id="updateByPrimaryKeySelective" parameterType="com.russellzhou.trade.data.entity.UserInfo">
    <!--
      WARNING - @mbg.generated
      This element is automatically generated by MyBatis Generator, do not modify.
    -->
    update user_info
    <set>
      <if test="userAccount != null">
        user_account = #{userAccount,jdbcType=VARCHAR},
      </if>
      <if test="userPassword != null">
        user_password = #{userPassword,jdbcType=VARCHAR},
      </if>
      <if test="userName != null">
        user_name = #{userName,jdbcType=VARCHAR},
      </if>
      <if test="email != null">
        email = #{email,jdbcType=VARCHAR},
      </if>
      <if test="mobile != null">
        mobile = #{mobile,jdbcType=VARCHAR},
      </if>
      <if test="isDel != null">
        is_del = #{isDel,jdbcType=TINYINT},
      </if>
      <if test="createTime != null">
        create_time = #{createTime,jdbcType=TIMESTAMP},
      </if>
      <if test="modifyTime != null">
        modify_time = #{modifyTime,jdbcType=TIMESTAMP},
      </if>
    </set>
    where id = #{id,jdbcType=BIGINT}
  </update>
  <update id="updateByPrimaryKey" parameterType="com.russellzhou.trade.data.entity.UserInfo">
    <!--
      WARNING - @mbg.generated
      This element is automatically generated by MyBatis Generator, do not modify.
    -->
    update user_info
    set user_account = #{userAccount,jdbcType=VARCHAR},
      user_password = #{userPassword,jdbcType=VARCHAR},
      user_name = #{userName,jdbcType=VARCHAR},
      email = #{email,jdbcType=VARCHAR},
      mobile = #{mobile,jdbcType=VARCHAR},
      is_del = #{isDel,jdbcType=TINYINT},
      create_time = #{createTime,jdbcType=TIMESTAMP},
      modify_time = #{modifyTime,jdbcType=TIMESTAMP}
    where id = #{id,jdbcType=BIGINT}
  </update>
</mapper>